pullama/__init__.py
pullama/diffchain/__init__.py
pullama/diffchain/chains.py
pullama/diffchain/prompts.py
pullama/pullama.py
pullama-0.1.5.dist-info/LICENSE
pullama-0.1.5.dist-info/METADATA
pullama-0.1.5.dist-info/WHEEL
pullama-0.1.5.dist-info/entry_points.txt
pullama-0.1.5.dist-info/RECORD
