Metadata-Version: 2.1
Name: pullama
Version: 0.1.5
Summary: A git diff Summarizer backed by LLM on Ollama
License: MIT
Author: Paulo Suzart
Author-email: paulo.suzart@getmoss.com
Requires-Python: >=3.11,<3.12
Classifier: License :: OSI Approved :: MIT License
Classifier: Programming Language :: Python :: 3
Classifier: Programming Language :: Python :: 3.11
Requires-Dist: click (>=8.1.7,<9.0.0)
Requires-Dist: esprima (>=4.0.1,<5.0.0)
Requires-Dist: fastembed (>=0.1.1,<0.2.0)
Requires-Dist: gitpython (>=3.1.40,<4.0.0)
Requires-Dist: langchain (>=0.0.350,<0.0.351)
Requires-Dist: qdrant-client (>=1.7.0,<2.0.0)
Requires-Dist: sync (>=1.0.0,<2.0.0)
Requires-Dist: unstructured (>=0.11.2,<0.12.0)
